{"data":[{"uri":"https://thetrove.net/Assets/By%20Artist%20or%20Source/Devin%20Night/Devin%20Token%20Pack%2045%20-%20Heroic%20Characters%201/Human_female_mage.png","imageType":["Token","Map Asset"],"setting":["Fantasy"],"style":["Stylized"],"quality":["Good"],"view":["Overhead"],"grid":["None"],"audience":["Player"],"hash":"c14a842c5a7638a0a210cf55d6785054"},{"uri":"https://thetrove.net/Assets/By%20Artist%20or%20Source/Devin%20Night/Devin%20Token%20Pack%2045%20-%20Heroic%20Characters%201/Human_Male_ClericofSheep.png","imageType":["Token","Map Asset"],"setting":["Fantasy"],"style":["Stylized"],"quality":["Good"],"view":["Overhead"],"grid":["None"],"audience":["Player"],"hash":"ff99640faec7c489346a23969c32e1fc"},{"uri":"https://thetrove.net/Assets/By%20Artist%20or%20Source/Devin%20Night/Devin%20Token%20Pack%2045%20-%20Heroic%20Characters%201/Human_Male_DruidBear.png","imageType":["Token","Map Asset"],"setting":["Fantasy"],"style":["Stylized"],"quality":["Good"],"view":["Overhead"],"grid":["None"],"audience":["Player"],"hash":"64a3276f6d919f46775b3f373f6b9412"},{"uri":"https://thetrove.net/Assets/By%20Artist%20or%20Source/Devin%20Night/Devin%20Token%20Pack%2045%20-%20Heroic%20Characters%201/Human_Male_FighterDoubleAxe.png","imageType":["Token","Map Asset"],"setting":["Fantasy"],"style":["Stylized"],"quality":["Good"],"view":["Overhead"],"grid":["None"],"audience":["Player"],"hash":"6104521e674c3027819e74dbcc8a1c63"},{"uri":"https://thetrove.net/Assets/By%20Artist%20or%20Source/Devin%20Night/Devin%20Token%20Pack%2045%20-%20Heroic%20Characters%201/Human_Male_Avenger_Khopesh.png","imageType":["Token","Map Asset"],"setting":["Fantasy"],"style":["Stylized"],"quality":["Good"],"view":["Overhead"],"grid":["None"],"audience":["Player"],"hash":"f8389191c835a1d383cd61739230e70a"},{"uri":"https://thetrove.net/Assets/By%20Artist%20or%20Source/Devin%20Night/Devin%20Token%20Pack%2045%20-%20Heroic%20Characters%201/human_Male_archer4.png","imageType":["Token","Map Asset"],"setting":["Fantasy"],"style":["Stylized"],"quality":["Good"],"view":["Overhead"],"grid":["None"],"audience":["Player"],"hash":"12550d328e76fbd69219fbfcb215c2c8"},{"uri":"https://thetrove.net/Assets/By%20Artist%20or%20Source/Devin%20Night/Devin%20Token%20Pack%2045%20-%20Heroic%20Characters%201/Human_Male_MageDandy.png","imageType":["Token","Map Asset"],"setting":["Fantasy"],"style":["Stylized"],"quality":["Good"],"view":["Overhead"],"grid":["None"],"audience":["Player"],"hash":"b6200dbdc950040d8feb5e3740e4c30b"},{"uri":"https://thetrove.net/Assets/By%20Artist%20or%20Source/Devin%20Night/Devin%20Token%20Pack%2045%20-%20Heroic%20Characters%201/Human_Male_Monk2.png","imageType":["Token","Map Asset"],"setting":["Fantasy"],"style":["Stylized"],"quality":["Good"],"view":["Overhead"],"grid":["None"],"audience":["Player"],"hash":"2ecc57273fb6e76d1f85acb59699f59a"},{"uri":"https://thetrove.net/Assets/By%20Artist%20or%20Source/Devin%20Night/Devin%20Token%20Pack%2045%20-%20Heroic%20Characters%201/Human_Male_PaladinHammer.png","imageType":["Token","Map Asset"],"setting":["Fantasy"],"style":["Stylized"],"quality":["Good"],"view":["Overhead"],"grid":["None"],"audience":["Player"],"hash":"429b2d1ef09b92e821f19cafa88945ad"},{"uri":"https://thetrove.net/Assets/By%20Artist%20or%20Source/Devin%20Night/Devin%20Token%20Pack%2045%20-%20Heroic%20Characters%201/Human_Female_Stuartslady.png","imageType":["Token","Map Asset"],"setting":["Fantasy"],"style":["Stylized"],"quality":["Good"],"view":["Overhead"],"grid":["None"],"audience":["Player"],"hash":"0b098bd161784df5a90b2f480e7ed68f"},{"uri":"https://thetrove.net/Assets/By%20Artist%20or%20Source/Devin%20Night/Devin%20Token%20Pack%2045%20-%20Heroic%20Characters%201/Human_Male_SwampguyCrossbow.png","imageType":["Token","Map Asset"],"setting":["Fantasy"],"style":["Stylized"],"quality":["Good"],"view":["Overhead"],"grid":["None"],"audience":["Player"],"hash":"6e5554836c3c1dde8159c4dcfab496d1"},{"uri":"https://thetrove.net/Assets/By%20Artist%20or%20Source/Devin%20Night/Devin%20Token%20Pack%2045%20-%20Heroic%20Characters%201/Human_Female_RangerAttacking.png","imageType":["Token","Map Asset"],"setting":["Fantasy"],"style":["Stylized"],"quality":["Good"],"view":["Overhead"],"grid":["None"],"audience":["Player"],"hash":"ab5eec32f68d8b9aaa73b668b9815a3e"},{"uri":"https://thetrove.net/Assets/By%20Artist%20or%20Source/Devin%20Night/Devin%20Token%20Pack%2045%20-%20Heroic%20Characters%201/Human_NorthmanMage.png","imageType":["Token","Map Asset"],"setting":["Fantasy"],"style":["Stylized"],"quality":["Good"],"view":["Overhead"],"grid":["None"],"audience":["Player"],"hash":"e41f3e94fe4547bdb28c2a8a0d993c33"},{"uri":"https://thetrove.net/Assets/By%20Artist%20or%20Source/Devin%20Night/Devin%20Token%20Pack%2045%20-%20Heroic%20Characters%201/Human_Male_Clericmomus.png","imageType":["Token","Map Asset"],"setting":["Fantasy"],"style":["Stylized"],"quality":["Good"],"view":["Overhead"],"grid":["None"],"audience":["Player"],"hash":"5713e16e27ac2ae1439ffed46d66d94d"},{"uri":"https://thetrove.net/Assets/By%20Artist%20or%20Source/Devin%20Night/Devin%20Token%20Pack%2045%20-%20Heroic%20Characters%201/Human_female_fighter.png","imageType":["Token","Map Asset"],"setting":["Fantasy"],"style":["Stylized"],"quality":["Good"],"view":["Overhead"],"grid":["None"],"audience":["Player"],"hash":"19dfbab61055d6970083dc3aedd182d9"},{"uri":"https://thetrove.net/Assets/By%20Artist%20or%20Source/Devin%20Night/Devin%20Token%20Pack%2045%20-%20Heroic%20Characters%201/Halfling_Rogue_Blue.png","imageType":["Token","Map Asset"],"setting":["Fantasy"],"style":["Stylized"],"quality":["Good"],"view":["Overhead"],"grid":["None"],"audience":["Player"],"hash":"ee552c35bcd2f1487a3ad91f7b4e6ad2"},{"uri":"https://thetrove.net/Assets/By%20Artist%20or%20Source/Devin%20Night/Devin%20Token%20Pack%2045%20-%20Heroic%20Characters%201/halfling_male_bard.png","imageType":["Token","Map Asset"],"setting":["Fantasy"],"style":["Stylized"],"quality":["Good"],"view":["Overhead"],"grid":["None"],"audience":["Player"],"hash":"ced9f71158b78f058d331f3c53487870"},{"uri":"https://thetrove.net/Assets/By%20Artist%20or%20Source/Devin%20Night/Devin%20Token%20Pack%2045%20-%20Heroic%20Characters%201/Goliath_Male_ooveklines.png","imageType":["Token","Map Asset"],"setting":["Fantasy"],"style":["Stylized"],"quality":["Good"],"view":["Overhead"],"grid":["None"],"audience":["Player"],"hash":"18d4f1f363093d93f7deedf3a7a8cf20"},{"uri":"https://thetrove.net/Assets/By%20Artist%20or%20Source/Devin%20Night/Devin%20Token%20Pack%2045%20-%20Heroic%20Characters%201/Elf_male_MagePerry.png","imageType":["Token","Map Asset"],"setting":["Fantasy"],"style":["Stylized"],"quality":["Good"],"view":["Overhead"],"grid":["None"],"audience":["Player"],"hash":"9d9f64457dbe874310a3ad230e3491e4"},{"uri":"https://thetrove.net/Assets/By%20Artist%20or%20Source/Devin%20Night/Devin%20Token%20Pack%2045%20-%20Heroic%20Characters%201/Elf_male_fighter.png","imageType":["Token","Map Asset"],"setting":["Fantasy"],"style":["Stylized"],"quality":["Good"],"view":["Overhead"],"grid":["None"],"audience":["Player"],"hash":"c4965596ab4ef512a9d3ace3dea4b569"},{"uri":"https://thetrove.net/Assets/By%20Artist%20or%20Source/Devin%20Night/Devin%20Token%20Pack%2045%20-%20Heroic%20Characters%201/Elf_Male_ArcherIconic.png","imageType":["Token","Map Asset"],"setting":["Fantasy"],"style":["Stylized"],"quality":["Good"],"view":["Overhead"],"grid":["None"],"audience":["Player"],"hash":"b34343fd2d152c8a96c7362e4128ee7c"},{"uri":"https://thetrove.net/Assets/By%20Artist%20or%20Source/Devin%20Night/Devin%20Token%20Pack%2045%20-%20Heroic%20Characters%201/Elf_female_Fighter.png","imageType":["Token","Map Asset"],"setting":["Fantasy"],"style":["Stylized"],"quality":["Good"],"view":["Overhead"],"grid":["None"],"audience":["Player"],"hash":"e1bb5345204708059e30f33abaac30b1"},{"uri":"https://thetrove.net/Assets/By%20Artist%20or%20Source/Devin%20Night/Devin%20Token%20Pack%2045%20-%20Heroic%20Characters%201/Elf_Female_Druid.png","imageType":["Token","Map Asset"],"setting":["Fantasy"],"style":["Stylized"],"quality":["Good"],"view":["Overhead"],"grid":["None"],"audience":["Player"],"hash":"5b57f678899c5530ab5cf0da76816ecc"},{"uri":"https://thetrove.net/Assets/By%20Artist%20or%20Source/Devin%20Night/Devin%20Token%20Pack%2045%20-%20Heroic%20Characters%201/Dwarf_Male_fighter.png","imageType":["Token","Map Asset"],"setting":["Fantasy"],"style":["Stylized"],"quality":["Good"],"view":["Overhead"],"grid":["None"],"audience":["Player"],"hash":"4ac1ff5073fd2e3377782883b79ef06f"},{"uri":"https://thetrove.net/Assets/By%20Artist%20or%20Source/Devin%20Night/Devin%20Token%20Pack%2045%20-%20Heroic%20Characters%201/Dwarf_Male_FighterToothaxe.png","imageType":["Token","Map Asset"],"setting":["Fantasy"],"style":["Stylized"],"quality":["Good"],"view":["Overhead"],"grid":["None"],"audience":["Player"],"hash":"5112ce61ca10ab52a27d7218663adf98"},{"uri":"https://thetrove.net/Assets/By%20Artist%20or%20Source/Devin%20Night/Devin%20Token%20Pack%2045%20-%20Heroic%20Characters%201/Dwarf_Male_Thoradin.png","imageType":["Token","Map Asset"],"setting":["Fantasy"],"style":["Stylized"],"quality":["Good"],"view":["Overhead"],"grid":["None"],"audience":["Player"],"hash":"ca3a0566675a7b37d5352123362c09b9"}],"artist":"Devin Night","set":"Devin Token Pack 45 - Heroic Characters 1"}